{
  "name": "Kantonswahlen Switzerland Schaffhausen",
  "country": "Schweiz",
  "source": "Kantonale Einzelfile-Konfiguration",
  "verificationMethod": "per-canton-file",
  "updatedAt": "2026-04-01T13:00:48Z",
  "regions": [
    {
      "regionCode": "SH",
      "regionName": "Schaffhausen",
      "electionType": "Kantonsparlamentswahl",
      "mapColorBasis": "staerkste Kraft nach letzter Kantonsparlamentswahl",
      "winningParty": "SVP",
      "winningPartyColor": "#247829",
      "sourceURL": "https://www.sh.ch/CMS/Webseite/Kanton-Schaffhausen/Beh-rde/Regierung/Staatskanzlei-15401466-DE.html",
      "lastElectionDate": "22.09.2024"
    }
  ]
}
